{"BaseModel.0dace2c3-ee1f-40ac-b59e-96bd4d148f68": {"id": "0dace2c3-ee1f-40ac-b59e-96bd4d148f68", "created_at": "2024-01-11T11:21:21.684438", "updated_at": "2024-01-11T11:21:44.996947", "name": "\"Diana\"", "__class__": "BaseModel"}, "BaseModel.4b2d3f97-8692-406c-b8c6-99f5933f7f8a": {"id": "4b2d3f97-8692-406c-b8c6-99f5933f7f8a", "created_at": "2024-01-11T11:27:30.240217", "updated_at": "2024-01-11T11:28:20.158660", "Diana": "\"Name\"", "__class__": "BaseModel"}, "BaseModel.6de9ddda-964d-477e-a63c-d61d229b9883": {"id": "6de9ddda-964d-477e-a63c-d61d229b9883", "created_at": "2024-01-11T14:08:05.913051", "updated_at": "2024-01-11T14:09:26.411006", "name": "Diana", "__class__": "BaseModel"}, "User.6937b4b9-9c77-4e19-85a6-461c793af4ae": {"id": "6937b4b9-9c77-4e19-85a6-461c793af4ae", "created_at": "2024-01-11T19:51:39.063965", "updated_at": "2024-01-11T19:51:39.106970", "first_name": "Betty", "last_name": "Bar", "email": "airbnb@mail.com", "password": "root", "__class__": "User"}, "User.bf5862d2-41a5-4c97-8fbe-015c12955f91": {"id": "bf5862d2-41a5-4c97-8fbe-015c12955f91", "created_at": "2024-01-12T08:21:06.151727", "updated_at": "2024-01-12T08:24:39.372723", "email": "diana@gmail.com", "password": "123", "firstname": "Diana", "lastname": "wangui", "__class__": "User"}}